api_24sea/ai/__init__.py
api_24sea/ai/core.py
api_24sea/ai/schemas.py
api_24sea/ai/utils.py
api_24sea/ai/version.py
api_24sea_ai-0.2.1.dist-info/licenses/LICENSE
api_24sea_ai-0.2.1.dist-info/WHEEL
api_24sea_ai-0.2.1.dist-info/METADATA
api_24sea_ai-0.2.1.dist-info/RECORD
