Metadata-Version: 2.4
Name: api-24sea-ai
Version: 0.2.1
Summary: Namespace package for api_24sea.ai, as indicated by PEP 420.
Author-email: Pietro D'Antuono <pietro.dantuono@24sea.eu>
Maintainer-email: Pietro D'Antuono <pietro.dantuono@24sea.eu>
Requires-Python: >=3.8.0,<3.14
Classifier: Development Status :: 3 - Alpha
Classifier: Environment :: Console
Classifier: Intended Audience :: Science/Research
Classifier: Intended Audience :: Information Technology
Classifier: License :: OSI Approved :: GNU General Public License v3 (GPLv3)
Classifier: Natural Language :: English
Classifier: Operating System :: POSIX :: Linux
Classifier: Programming Language :: Python :: 3
Classifier: Programming Language :: Python :: 3.8
Classifier: Programming Language :: Python :: 3.9
Classifier: Programming Language :: Python :: 3.10
Classifier: Programming Language :: Python :: 3.11
Classifier: Programming Language :: Python :: 3.12
Classifier: Programming Language :: Python :: 3.13
License-File: LICENSE
Requires-Dist: api-24sea>=2.1.5,<3.0.0
Requires-Dist: pandas<2.0.0; python_version<'3.10'
Requires-Dist: pandas>=2.1.0; python_version>='3.10'
Project-URL: 24SEA API Homepage, https://api.24SEA.eu/redoc/v1/
Project-URL: Documentation, https://api24seapydocs.z6.web.core.windows.net/ai
Project-URL: Homepage, https://24SEA.eu
Project-URL: Repository, https://bitbucket.org/24sea/api-24sea-ai-pkg
